vigil_science/__init__.py
vigil_science/cli.py
vigil_science-0.3.10.dist-info/METADATA
vigil_science-0.3.10.dist-info/WHEEL
vigil_science-0.3.10.dist-info/entry_points.txt
vigil_science-0.3.10.dist-info/licenses/LICENSE
vigil_science-0.3.10.dist-info/RECORD
