Metadata-Version: 2.4
Name: vigil-science
Version: 0.3.10
Summary: Vigil Science: Complete reproducible science platform
Project-URL: Homepage, https://vigil.cofactor.app
Project-URL: Documentation, https://docs.vigil.cofactor.app
Project-URL: Repository, https://github.com/cofactor/vigil
Project-URL: Issues, https://github.com/cofactor/vigil/issues
Author: Science Abundance
License: Apache-2.0
License-File: LICENSE
Keywords: cli,cryptography,provenance,reproducible,science
Classifier: Development Status :: 4 - Beta
Classifier: Intended Audience :: Science/Research
Classifier: License :: OSI Approved :: Apache Software License
Classifier: Operating System :: OS Independent
Classifier: Programming Language :: Python :: 3
Classifier: Programming Language :: Python :: 3.11
Classifier: Programming Language :: Python :: 3.12
Classifier: Programming Language :: Python :: 3.13
Classifier: Topic :: Scientific/Engineering
Classifier: Topic :: Software Development :: Libraries :: Python Modules
Requires-Python: >=3.11
Requires-Dist: vigil-client>=0.3.10
Requires-Dist: vigil-core>=0.3.10
